setup.py
es_loghandler/__init__.py
es_loghandler/handlers.py
es_loghandler.egg-info/PKG-INFO
es_loghandler.egg-info/SOURCES.txt
es_loghandler.egg-info/dependency_links.txt
es_loghandler.egg-info/requires.txt
es_loghandler.egg-info/top_level.txt