Metadata-Version: 1.0
Name: es-loghandler
Version: 0.0.5
Summary: Elasticsearch log handler.
Home-page: https://github.com/telminov/python-elasticsearch-loghandler
Author: Telminov Sergey
Author-email: UNKNOWN
License: The MIT License
Platform: UNKNOWN
